{
  "asOf": "2026-03-31",
  "cadence": "quarterly",
  "coverage": "CESC",
  "data": {
    "cmp": 167,
    "confidence": "high",
    "ebitdaMarginPct": 18.6,
    "hasDetail": false,
    "marketCapCr": 22100,
    "name": "CESC",
    "patFy26Cr": 1618,
    "peX": 14.3,
    "revenueFy26Cr": 18570,
    "slug": "cesc",
    "sourceNote": "Market data (mid-2026) + company filings",
    "tickerNse": "CESC",
    "type": "utility"
  },
  "dataset": "detail/cesc",
  "notes": [
    "Registry-level identity only; a detail JSON has not been added yet (model + manual approach)."
  ],
  "section": "companies",
  "sources": [
    {
      "asOf": "2026-03-31",
      "confidence": "high",
      "name": "Market data (mid-2026) + company filings"
    }
  ],
  "updatedAt": "2026-03-31"
}
