{
  "asOf": "2026-03-31",
  "cadence": "quarterly",
  "coverage": "India · solar PV manufacturing value chain (cells, modules, wafers)",
  "data": {
    "almmTimeline": [
      {
        "confidence": "high",
        "effectiveDate": "2021-04-01",
        "phase": "ALMM-I",
        "scope": "Modules — 173 GW enlisted",
        "status": "Active"
      },
      {
        "confidence": "high",
        "effectiveDate": "2026-06-01",
        "phase": "ALMM-II",
        "scope": "Cells — ~27 GW enlisted",
        "status": "Effective Jun 2026"
      },
      {
        "confidence": "medium",
        "effectiveDate": "2028-06-01",
        "phase": "ALMM-III",
        "scope": "Wafers",
        "status": "Announced"
      }
    ],
    "cellPlayers": [
      {
        "almm2Gw": 5.251,
        "confidence": "high",
        "nameplateGw": 5.4,
        "player": "Waaree",
        "productionGw": 2.283,
        "utilizationPct": 44
      },
      {
        "almm2Gw": 4.813,
        "confidence": "high",
        "nameplateGw": 4.813,
        "player": "Tata Power",
        "productionGw": 3.683,
        "utilizationPct": 76
      },
      {
        "almm2Gw": 4.237,
        "confidence": "high",
        "nameplateGw": 4,
        "player": "Mundra (Adani)",
        "productionGw": 2.693,
        "utilizationPct": 62
      },
      {
        "almm2Gw": 3.283,
        "confidence": "high",
        "nameplateGw": 3.6,
        "player": "Premier",
        "productionGw": 2.235,
        "utilizationPct": 80
      },
      {
        "almm2Gw": 3.433,
        "confidence": "high",
        "nameplateGw": 3.433,
        "player": "First Solar",
        "productionGw": 2.84,
        "utilizationPct": 83
      },
      {
        "almm2Gw": 1.553,
        "confidence": "high",
        "nameplateGw": 2.9,
        "note": "not yet DCR-enlisted",
        "player": "Emmvee",
        "productionGw": 1.6,
        "utilizationPct": 103
      },
      {
        "almm2Gw": 1.766,
        "confidence": "high",
        "nameplateGw": 2.5,
        "note": "not yet DCR-enlisted",
        "player": "ReNew",
        "productionGw": 1.845,
        "utilizationPct": 105
      },
      {
        "almm2Gw": 1.77,
        "confidence": "high",
        "nameplateGw": 2,
        "player": "Jupiter",
        "productionGw": 0.726,
        "utilizationPct": 80
      },
      {
        "almm2Gw": 1.238,
        "confidence": "medium",
        "nameplateGw": 1.24,
        "note": "not yet producing",
        "player": "Reliance"
      },
      {
        "almm2Gw": 1.074,
        "confidence": "high",
        "nameplateGw": 1.2,
        "player": "Evervolt",
        "productionGw": 0.382,
        "utilizationPct": 34
      },
      {
        "almm2Gw": 1.202,
        "confidence": "high",
        "nameplateGw": 1.2,
        "player": "Websol",
        "productionGw": 0.699,
        "utilizationPct": 77
      },
      {
        "almm2Gw": 0.437,
        "confidence": "high",
        "nameplateGw": 1,
        "player": "UTL Solar",
        "productionGw": 0.11,
        "utilizationPct": 44
      }
    ],
    "cellQuarterly": {
      "categories": [
        "Q1FY26",
        "Q2FY26",
        "Q3FY26",
        "Q4FY26"
      ],
      "series": [
        {
          "color": "#2563EB",
          "key": "tata-power",
          "label": "Tata Power",
          "values": [
            0.81,
            0.884,
            0.958,
            1.031
          ]
        },
        {
          "color": "#F59E0B",
          "key": "first-solar",
          "label": "First Solar",
          "values": [
            0.625,
            0.682,
            0.738,
            0.795
          ]
        },
        {
          "color": "#10B981",
          "key": "mundra-adani",
          "label": "Mundra (Adani)",
          "values": [
            0.592,
            0.646,
            0.7,
            0.754
          ]
        },
        {
          "color": "#8B5CF6",
          "key": "waaree",
          "label": "Waaree",
          "values": [
            0.502,
            0.548,
            0.594,
            0.639
          ]
        },
        {
          "color": "#EC4899",
          "key": "premier",
          "label": "Premier",
          "values": [
            0.492,
            0.536,
            0.581,
            0.626
          ]
        },
        {
          "color": "#94A3B8",
          "key": "others",
          "label": "Others",
          "values": [
            1.18,
            1.287,
            1.394,
            1.501
          ]
        }
      ]
    },
    "cellTrajectory": [
      {
        "color": "#64748B",
        "key": "existing",
        "label": "Existing",
        "points": [
          {
            "period": "FY26E",
            "value": 19
          },
          {
            "period": "FY27E",
            "value": 32
          },
          {
            "period": "FY28E",
            "value": 50
          }
        ],
        "unit": "GW"
      },
      {
        "color": "#F59E0B",
        "key": "new",
        "label": "New",
        "points": [
          {
            "period": "FY26E",
            "value": 0
          },
          {
            "period": "FY27E",
            "value": 6
          },
          {
            "period": "FY28E",
            "value": 14
          }
        ],
        "unit": "GW"
      }
    ],
    "economics": [
      {
        "confidence": "medium",
        "metric": "Cell realisation (current)",
        "unit": "USD/Wp",
        "value": 0.14
      },
      {
        "confidence": "medium",
        "metric": "Cell realisation (forecast)",
        "unit": "USD/Wp",
        "value": 0.1
      },
      {
        "confidence": "medium",
        "metric": "Cell EBITDA/Wp",
        "unit": "USD/Wp",
        "value": 0.07
      },
      {
        "confidence": "medium",
        "metric": "DCR cell premium vs China (now)",
        "unit": "%",
        "value": 75
      },
      {
        "confidence": "medium",
        "metric": "DCR cell premium vs China (FY28E)",
        "unit": "%",
        "value": 40
      },
      {
        "confidence": "medium",
        "metric": "Cell capex intensity",
        "unit": "Rs_cr/GW",
        "value": 600
      },
      {
        "confidence": "medium",
        "metric": "Wafer+cell capex intensity",
        "unit": "Rs_cr/GW",
        "value": 1200
      },
      {
        "confidence": "medium",
        "metric": "TOPCon module price",
        "unit": "Rs/Wp",
        "value": 22
      },
      {
        "confidence": "medium",
        "metric": "DCR premium over non-DCR",
        "unit": "Rs/Wp",
        "value": 4
      },
      {
        "confidence": "medium",
        "metric": "Polysilicon (China mono)",
        "unit": "USD/kg",
        "value": 4.99
      }
    ],
    "kpis": [
      {
        "confidence": "high",
        "hint": "MNRE Mar 2026",
        "key": "module_capacity",
        "label": "Module capacity (ALMM-I)",
        "unit": "GW",
        "value": 173
      },
      {
        "confidence": "high",
        "hint": "~27 GW enlisted",
        "key": "cell_capacity",
        "label": "Cell capacity (ALMM-II)",
        "unit": "GW",
        "value": 27
      },
      {
        "confidence": "high",
        "hint": "VQ · modelled quarterly split",
        "key": "cell_production",
        "label": "Cell production FY26E",
        "unit": "GW",
        "value": 19.1
      },
      {
        "confidence": "high",
        "hint": "VQ · production ÷ ALMM-II",
        "key": "utilization",
        "label": "Avg cell utilisation",
        "unit": "%",
        "value": 66.3
      },
      {
        "confidence": "medium",
        "hint": "VQ · domestic-content",
        "key": "dcr_demand",
        "label": "DCR module demand FY26E",
        "unit": "GW",
        "value": 18
      },
      {
        "confidence": "high",
        "hint": "173 ÷ 58 GW (FY26)",
        "key": "overcapacity",
        "label": "Module overcapacity",
        "unit": "x",
        "value": 3
      }
    ],
    "moduleDemand": [
      {
        "color": "#64748B",
        "key": "non-dcr",
        "label": "Non-DCR",
        "points": [
          {
            "period": "FY26E",
            "value": 40
          },
          {
            "period": "FY27E",
            "value": 35
          },
          {
            "period": "FY28E",
            "value": 32
          }
        ],
        "unit": "GW"
      },
      {
        "color": "#F59E0B",
        "key": "dcr",
        "label": "DCR",
        "points": [
          {
            "period": "FY26E",
            "value": 18
          },
          {
            "period": "FY27E",
            "value": 32
          },
          {
            "period": "FY28E",
            "value": 55
          }
        ],
        "unit": "GW"
      }
    ],
    "modulePlayers": [
      {
        "almm1Gw": 15,
        "confidence": "high",
        "player": "Waaree"
      },
      {
        "almm1Gw": 11.1,
        "confidence": "high",
        "player": "Premier Energies"
      },
      {
        "almm1Gw": 7.8,
        "confidence": "medium",
        "player": "Emmvee"
      },
      {
        "almm1Gw": 6,
        "confidence": "medium",
        "player": "ReNew"
      },
      {
        "almm1Gw": 4.9,
        "confidence": "medium",
        "player": "Tata Power Solar"
      },
      {
        "almm1Gw": 4.5,
        "confidence": "medium",
        "player": "Vikram Solar"
      },
      {
        "almm1Gw": 4,
        "confidence": "medium",
        "player": "Adani Solar"
      },
      {
        "almm1Gw": 3.8,
        "confidence": "medium",
        "player": "Saatvik"
      },
      {
        "almm1Gw": 3,
        "confidence": "medium",
        "player": "Goldi Solar"
      },
      {
        "almm1Gw": 112.9,
        "confidence": "medium",
        "player": "Others"
      }
    ],
    "pliAwardees": [
      {
        "capacityGw": 10,
        "company": "Reliance",
        "confidence": "high"
      },
      {
        "capacityGw": 6,
        "company": "Waaree",
        "confidence": "high"
      },
      {
        "capacityGw": 4.8,
        "company": "ReNew",
        "confidence": "high"
      },
      {
        "capacityGw": 4,
        "company": "Adani",
        "confidence": "high"
      },
      {
        "capacityGw": 4,
        "company": "Shirdi Sai Electricals",
        "confidence": "high"
      },
      {
        "capacityGw": 4,
        "company": "Tata Power",
        "confidence": "high"
      },
      {
        "capacityGw": 3.4,
        "company": "First Solar",
        "confidence": "high"
      },
      {
        "capacityGw": 2.4,
        "company": "Vikram Solar",
        "confidence": "high"
      },
      {
        "capacityGw": 9.7,
        "company": "Others",
        "confidence": "medium"
      }
    ],
    "supplyDemand": [
      {
        "capacityFy26": 173,
        "capacityFy28": 210,
        "demandFy26": 58,
        "demandFy28": 87,
        "segment": "module"
      },
      {
        "capacityFy26": 27,
        "capacityFy28": 60,
        "demandFy26": 58,
        "demandFy28": 87,
        "segment": "cell"
      }
    ],
    "wafer": [
      {
        "demandGw": 35,
        "period": "FY29E",
        "supplyGw": 25
      },
      {
        "demandGw": 50,
        "period": "FY30E",
        "supplyGw": 35
      },
      {
        "demandGw": 70,
        "period": "FY31E",
        "supplyGw": 50
      }
    ]
  },
  "dataset": "value-chain",
  "notes": [
    "Quarterly cell production is MODELLED: each producer's FY26E annual output is split across Q1FY26/Q2FY26/Q3FY26/Q4FY26 with a ramp [0.22, 0.24, 0.26, 0.28]; drop real (player, quarter) actuals into manufacturing/cell-production-quarterly-override.csv to override a cell.",
    "Module capacity is 173 GW enlisted under ALMM-I (MNRE Mar 2026; long tail bucketed as Others); the cell headline is ~27 GW ALMM-II (MNRE Feb 2026).",
    "The player-wise cell-capacity, module-demand, cell-trajectory and wafer tables are VQ Research (early 2026); PLI Tranche I+II awardees total ~48 GW (PIB / JMK).",
    "Basic Customs Duty (BCD): modules 40% / cells 27.5%."
  ],
  "section": "manufacturing",
  "sources": [
    {
      "asOf": "2026-03-31",
      "confidence": "medium",
      "name": "Company"
    },
    {
      "asOf": "2026-03-31",
      "confidence": "high",
      "name": "Company FY26"
    },
    {
      "asOf": "2026-03-31",
      "confidence": "medium",
      "name": "Market 2026"
    },
    {
      "asOf": "2026-03-31",
      "confidence": "high",
      "name": "Mercom / MNRE / CareEdge"
    },
    {
      "asOf": "2026-03-31",
      "confidence": "medium",
      "name": "MNRE"
    },
    {
      "asOf": "2026-03-31",
      "confidence": "high",
      "name": "MNRE / CareEdge"
    },
    {
      "asOf": "2026-03-31",
      "confidence": "high",
      "name": "MNRE / DCR Portal"
    },
    {
      "asOf": "2026-03-31",
      "confidence": "medium",
      "name": "MNRE / DCR Portal"
    },
    {
      "asOf": "2026-03-31",
      "confidence": "medium",
      "name": "MNRE ALMM List-I"
    },
    {
      "asOf": "2026-03-31",
      "confidence": "high",
      "name": "MNRE Feb 2026",
      "url": "https://mnre.gov.in/en/approved-list-of-models-and-manufacturers/"
    },
    {
      "asOf": "2026-03-31",
      "confidence": "high",
      "name": "MNRE Mar 2026",
      "url": "https://mnre.gov.in/en/approved-list-of-models-and-manufacturers/"
    },
    {
      "asOf": "2026-03-31",
      "confidence": "high",
      "name": "PIB"
    },
    {
      "asOf": "2026-03-31",
      "confidence": "high",
      "name": "PIB / JMK"
    },
    {
      "asOf": "2026-03-31",
      "confidence": "medium",
      "name": "PIB / JMK"
    },
    {
      "asOf": "2026-03-31",
      "confidence": "medium",
      "name": "PVInsights Apr 2026"
    },
    {
      "asOf": "2026-03-31",
      "confidence": "medium",
      "name": "VQ / PL Capital"
    },
    {
      "asOf": "2026-03-31",
      "confidence": "medium",
      "name": "VQ Research"
    }
  ],
  "updatedAt": "2026-03-31"
}
